djangouniversallogger/__init__.py
djangouniversallogger/admin.py
djangouniversallogger/apps.py
djangouniversallogger/decorators.py
djangouniversallogger/logger_.py
djangouniversallogger/models.py
djangouniversallogger/tests.py
djangouniversallogger/utils.py
djangouniversallogger/views.py
django_universal_logger-0.0.3.dist-info/METADATA
django_universal_logger-0.0.3.dist-info/WHEEL
django_universal_logger-0.0.3.dist-info/top_level.txt
django_universal_logger-0.0.3.dist-info/RECORD
